confluent_kafka_connect_cli/__init__.py
confluent_kafka_connect_cli/call.py
confluent_kafka_connect_cli/cli.py
confluent_kafka_connect_cli-0.3.0.dist-info/AUTHORS.rst
confluent_kafka_connect_cli-0.3.0.dist-info/LICENSE
confluent_kafka_connect_cli-0.3.0.dist-info/METADATA
confluent_kafka_connect_cli-0.3.0.dist-info/WHEEL
confluent_kafka_connect_cli-0.3.0.dist-info/entry_points.txt
confluent_kafka_connect_cli-0.3.0.dist-info/top_level.txt
confluent_kafka_connect_cli-0.3.0.dist-info/RECORD
