Metadata-Version: 2.1
Name: confluent-kafka-connect-cli
Version: 0.3.0
Summary: Make it easier to interact with the confluent kafka connect REST api.
Home-page: https://github.com/aidan-melen/confluent_kafka_connect_cli
Author: Aidan Melen
Author-email: aidan-melen@pluralsight.com
License: MIT license
Keywords: confluent_kafka_connect_cli
Platform: UNKNOWN
Classifier: Development Status :: 2 - Pre-Alpha
Classifier: Intended Audience :: Developers
Classifier: License :: OSI Approved :: MIT License
Classifier: Natural Language :: English
Classifier: Programming Language :: Python :: 3
Classifier: Programming Language :: Python :: 3.5
Classifier: Programming Language :: Python :: 3.6
Classifier: Programming Language :: Python :: 3.7
Classifier: Programming Language :: Python :: 3.8
Requires-Python: >=3.5
Requires-Dist: Click (>=7.0)
Requires-Dist: requests (>=2.22.0)
